tarebar/__init__.py
tarebar/tarebar.py
tarebar-1.2.dist-info/LICENSE
tarebar-1.2.dist-info/METADATA
tarebar-1.2.dist-info/WHEEL
tarebar-1.2.dist-info/top_level.txt
tarebar-1.2.dist-info/RECORD
