Metadata-Version: 2.1
Name: tarebar
Version: 1.2
Summary: A world of numbers and functions.
Author-email: Mohammad Parsa Mortazavi <mpmms@outlook.com>, Aliakbar Mohammadi Saaei <aamshelli@gmail.com>
Classifier: Programming Language :: Python :: 3
Classifier: License :: OSI Approved :: MIT License
Classifier: Operating System :: OS Independent
Requires-Python: >=3.0
License-File: LICENSE
